daq2lh5/__init__.py
daq2lh5/_version.py
daq2lh5/build_raw.py
daq2lh5/cli.py
daq2lh5/data_decoder.py
daq2lh5/data_streamer.py
daq2lh5/logging.py
daq2lh5/raw_buffer.py
daq2lh5/utils.py
daq2lh5/buffer_processor/__init__.py
daq2lh5/buffer_processor/buffer_processor.py
daq2lh5/buffer_processor/lh5_buffer_processor.py
daq2lh5/compass/__init__.py
daq2lh5/compass/compass_config_parser.py
daq2lh5/compass/compass_event_decoder.py
daq2lh5/compass/compass_header_decoder.py
daq2lh5/compass/compass_streamer.py
daq2lh5/fc/__init__.py
daq2lh5/fc/fc_config_decoder.py
daq2lh5/fc/fc_event_decoder.py
daq2lh5/fc/fc_eventheader_decoder.py
daq2lh5/fc/fc_fsp_decoder.py
daq2lh5/fc/fc_status_decoder.py
daq2lh5/fc/fc_streamer.py
daq2lh5/llama/__init__.py
daq2lh5/llama/llama_base.py
daq2lh5/llama/llama_event_decoder.py
daq2lh5/llama/llama_header_decoder.py
daq2lh5/llama/llama_streamer.py
daq2lh5/orca/__init__.py
daq2lh5/orca/orca_base.py
daq2lh5/orca/orca_digitizers.py
daq2lh5/orca/orca_fcio.py
daq2lh5/orca/orca_flashcam.py
daq2lh5/orca/orca_header.py
daq2lh5/orca/orca_header_decoder.py
daq2lh5/orca/orca_packet.py
daq2lh5/orca/orca_run_decoder.py
daq2lh5/orca/orca_streamer.py
daq2lh5/orca/skim_orca_file.py
legend_daq2lh5-1.6.3.dist-info/licenses/LICENSE
legend_daq2lh5-1.6.3.dist-info/METADATA
legend_daq2lh5-1.6.3.dist-info/WHEEL
legend_daq2lh5-1.6.3.dist-info/entry_points.txt
legend_daq2lh5-1.6.3.dist-info/top_level.txt
legend_daq2lh5-1.6.3.dist-info/RECORD
