Metadata-Version: 2.4
Name: legend-daq2lh5
Version: 1.6.3
Summary: Convert digitizer data to LH5
Author-email: Jason Detwiler <jasondet@uw.edu>
Maintainer: The LEGEND collaboration
Project-URL: Homepage, https://github.com/legend-exp/legend-daq2lh5
Project-URL: Bug Tracker, https://github.com/legend-exp/legend-daq2lh5/issues
Project-URL: Discussions, https://github.com/legend-exp/legend-daq2lh5/discussions
Project-URL: Changelog, https://github.com/legend-exp/legend-daq2lh5/releases
Classifier: Development Status :: 4 - Beta
Classifier: Intended Audience :: Developers
Classifier: Intended Audience :: Science/Research
Classifier: License :: OSI Approved :: GNU General Public License v3 (GPLv3)
Classifier: Operating System :: MacOS
Classifier: Operating System :: POSIX
Classifier: Operating System :: Unix
Classifier: Programming Language :: Python
Classifier: Programming Language :: Python :: 3
Classifier: Programming Language :: Python :: 3 :: Only
Classifier: Topic :: Scientific/Engineering
Requires-Python: >=3.9
License-File: LICENSE
Requires-Dist: dspeed>=1.3
Requires-Dist: fcio>=0.7.9
Requires-Dist: h5py>=3.2.0
Requires-Dist: hdf5plugin
Requires-Dist: legend-pydataobj>=1.6
Requires-Dist: numpy>=1.21
Requires-Dist: pyyaml
Requires-Dist: tqdm>=4.27
Requires-Dist: xmltodict
Provides-Extra: all
Requires-Dist: legend-daq2lh5[docs,test]; extra == "all"
Provides-Extra: docs
Requires-Dist: furo; extra == "docs"
Requires-Dist: jupyter; extra == "docs"
Requires-Dist: myst-parser; extra == "docs"
Requires-Dist: nbsphinx; extra == "docs"
Requires-Dist: sphinx; extra == "docs"
Requires-Dist: sphinx-copybutton; extra == "docs"
Requires-Dist: sphinx-inline-tabs; extra == "docs"
Provides-Extra: test
Requires-Dist: pre-commit; extra == "test"
Requires-Dist: pylegendtestdata; extra == "test"
Requires-Dist: pytest>=6.0; extra == "test"
Requires-Dist: pytest-cov; extra == "test"
Dynamic: license-file
